{
    "stationName": "勝沼ぶどう郷",
    "lineName": "中央本線 上り",
    "trainTypes": [
        "特急 あずさ50号",
        "特急 あずさ26号",
        "特急 あずさ42号",
        "中央特快",
        "特急 あずさ44号",
        "特急 かいじ14号",
        "特急 かいじ24号",
        "特急 かいじ58号",
        "特急 あずさ16号",
        "特急 あずさ18号",
        "快速 みすず",
        "特急 あずさ22号",
        "特急 あずさ8号",
        "特急 かいじ20号",
        "特急 かいじ10号",
        "特急 あずさ38号",
        "特急 あずさ60号",
        "特急 はちおうじ4号",
        "特急 かいじ32号",
        "特急 富士回遊44号",
        "特急 あずさ12号",
        "特急 かいじ48号",
        "快速",
        "特急 かいじ56号",
        "通勤特別快速",
        "特急 おうめ2号",
        "普通",
        "特急 かいじ2号",
        "特急 あずさ4号",
        "普通 むさしの号",
        "特急 富士回遊36号",
        "特急 あずさ34号",
        "特急 富士回遊48号",
        "特急 かいじ6号",
        "特急 あずさ46号",
        "特急 かいじ36号",
        "特急 あずさ54号",
        "特急 かいじ40号",
        "特急 かいじ28号",
        "特急 かいじ52号",
        "特急 あずさ30号",
        "特急 はちおうじ2号"
    ],
    "trainDestinations": [
        "高尾",
        "茅野",
        "立川",
        "塩山",
        "富士見",
        "千葉"
    ],
    "isHoliday": false,
    "trainSchedules": {
        "0554": {
            "type": 26,
            "dst": 0
        },
        "0617": {
            "type": 26,
            "dst": 0
        },
        "0641": {
            "type": 26,
            "dst": 0
        },
        "0708": {
            "type": 26,
            "dst": 2
        },
        "0745": {
            "type": 26,
            "dst": 0
        },
        "0817": {
            "type": 26,
            "dst": 0
        },
        "0844": {
            "type": 26,
            "dst": 0
        },
        "0918": {
            "type": 26,
            "dst": 0
        },
        "0949": {
            "type": 26,
            "dst": 0
        },
        "1016": {
            "type": 26,
            "dst": 0
        },
        "1059": {
            "type": 26,
            "dst": 0
        },
        "1154": {
            "type": 26,
            "dst": 0
        },
        "1210": {
            "type": 26,
            "dst": 0
        },
        "1310": {
            "type": 26,
            "dst": 0
        },
        "1417": {
            "type": 26,
            "dst": 0
        },
        "1518": {
            "type": 26,
            "dst": 0
        },
        "1557": {
            "type": 26,
            "dst": 0
        },
        "1635": {
            "type": 26,
            "dst": 0
        },
        "1725": {
            "type": 26,
            "dst": 2
        },
        "1811": {
            "type": 26,
            "dst": 0
        },
        "1832": {
            "type": 26,
            "dst": 0
        },
        "1904": {
            "type": 26,
            "dst": 0
        },
        "1925": {
            "type": 26,
            "dst": 5
        },
        "2010": {
            "type": 26,
            "dst": 5
        },
        "2032": {
            "type": 26,
            "dst": 0
        },
        "2104": {
            "type": 26,
            "dst": 5
        },
        "2123": {
            "type": 26,
            "dst": 0
        },
        "2201": {
            "type": 26,
            "dst": 0
        },
        "2233": {
            "type": 26,
            "dst": 0
        },
        "2258": {
            "type": 26,
            "dst": 5
        }
    }
}