{
    "stationName": "浦和",
    "lineName": "湘南新宿ライン 北行",
    "trainTypes": [
        "特急 スペーシアきぬがわ11号",
        "特急 踊り子18号",
        "特急 スペーシアきぬがわ7号",
        "特別快速",
        "特急 日光1号",
        "特急 スペーシアきぬがわ3号",
        "特急 きぬがわ11号",
        "快速",
        "特急 きぬがわ5号",
        "普通"
    ],
    "trainDestinations": [
        "小山",
        "池袋"
    ],
    "isHoliday": true,
    "trainTimes": [
        723,
        746,
        754,
        802,
        834,
        850,
        904,
        914,
        934,
        950,
        1006,
        1019,
        1030,
        1038,
        1054,
        1101,
        1110,
        1115,
        1134,
        1144,
        1204,
        1213,
        1233,
        1244,
        1304,
        1314,
        1323,
        1334,
        1344,
        1404,
        1413,
        1433,
        1444,
        1504,
        1513,
        1534,
        1544,
        1604,
        1613,
        1634,
        1644,
        1706,
        1713,
        1734,
        1748,
        1755,
        1804,
        1815,
        1834,
        1850,
        1900,
        1919,
        1935,
        1943,
        1951,
        2004,
        2018,
        2036,
        2049,
        2103,
        2119,
        2135,
        2150,
        2208,
        2229,
        2248,
        2311,
        2324,
        2359
    ],
    "trainDetails": {
        "0723": {
            "type": 7,
            "dst": 0
        },
        "0746": {
            "type": 9,
            "dst": 0
        },
        "0754": {
            "type": 4,
            "dst": 0
        },
        "0802": {
            "type": 7,
            "dst": 0
        },
        "0834": {
            "type": 9,
            "dst": 0
        },
        "0850": {
            "type": 7,
            "dst": 0
        },
        "0904": {
            "type": 9,
            "dst": 0
        },
        "0914": {
            "type": 7,
            "dst": 0
        },
        "0934": {
            "type": 9,
            "dst": 0
        },
        "0950": {
            "type": 7,
            "dst": 0
        },
        "1006": {
            "type": 7,
            "dst": 0
        },
        "1019": {
            "type": 9,
            "dst": 0
        },
        "1030": {
            "type": 6,
            "dst": 0
        },
        "1038": {
            "type": 3,
            "dst": 0
        },
        "1054": {
            "type": 5,
            "dst": 0
        },
        "1101": {
            "type": 7,
            "dst": 0
        },
        "1110": {
            "type": 9,
            "dst": 0
        },
        "1115": {
            "type": 7,
            "dst": 0
        },
        "1134": {
            "type": 7,
            "dst": 0
        },
        "1144": {
            "type": 3,
            "dst": 0
        },
        "1204": {
            "type": 9,
            "dst": 0
        },
        "1213": {
            "type": 7,
            "dst": 0
        },
        "1233": {
            "type": 7,
            "dst": 0
        },
        "1244": {
            "type": 3,
            "dst": 0
        },
        "1304": {
            "type": 9,
            "dst": 0
        },
        "1314": {
            "type": 7,
            "dst": 0
        },
        "1323": {
            "type": 8,
            "dst": 0
        },
        "1334": {
            "type": 7,
            "dst": 0
        },
        "1344": {
            "type": 3,
            "dst": 0
        },
        "1404": {
            "type": 9,
            "dst": 0
        },
        "1413": {
            "type": 7,
            "dst": 0
        },
        "1433": {
            "type": 7,
            "dst": 0
        },
        "1444": {
            "type": 3,
            "dst": 0
        },
        "1504": {
            "type": 9,
            "dst": 0
        },
        "1513": {
            "type": 7,
            "dst": 0
        },
        "1534": {
            "type": 7,
            "dst": 0
        },
        "1544": {
            "type": 3,
            "dst": 0
        },
        "1604": {
            "type": 9,
            "dst": 0
        },
        "1613": {
            "type": 7,
            "dst": 0
        },
        "1634": {
            "type": 7,
            "dst": 0
        },
        "1644": {
            "type": 3,
            "dst": 0
        },
        "1706": {
            "type": 9,
            "dst": 0
        },
        "1713": {
            "type": 7,
            "dst": 0
        },
        "1734": {
            "type": 7,
            "dst": 0
        },
        "1748": {
            "type": 3,
            "dst": 0
        },
        "1755": {
            "type": 2,
            "dst": 0
        },
        "1804": {
            "type": 9,
            "dst": 0
        },
        "1815": {
            "type": 7,
            "dst": 0
        },
        "1834": {
            "type": 9,
            "dst": 0
        },
        "1850": {
            "type": 7,
            "dst": 0
        },
        "1900": {
            "type": 9,
            "dst": 0
        },
        "1919": {
            "type": 7,
            "dst": 0
        },
        "1935": {
            "type": 9,
            "dst": 0
        },
        "1943": {
            "type": 7,
            "dst": 0
        },
        "1951": {
            "type": 7,
            "dst": 0
        },
        "2004": {
            "type": 9,
            "dst": 0
        },
        "2018": {
            "type": 7,
            "dst": 0
        },
        "2036": {
            "type": 9,
            "dst": 0
        },
        "2049": {
            "type": 7,
            "dst": 0
        },
        "2103": {
            "type": 7,
            "dst": 0
        },
        "2119": {
            "type": 9,
            "dst": 0
        },
        "2135": {
            "type": 7,
            "dst": 0
        },
        "2150": {
            "type": 9,
            "dst": 0
        },
        "2208": {
            "type": 7,
            "dst": 0
        },
        "2229": {
            "type": 9,
            "dst": 0
        },
        "2248": {
            "type": 7,
            "dst": 0
        },
        "2311": {
            "type": 9,
            "dst": 0
        },
        "2324": {
            "type": 7,
            "dst": 0
        },
        "2359": {
            "type": 7,
            "dst": 0
        }
    }
}