{
    "stationName": "日暮里",
    "lineName": "山手線 外回り",
    "trainTypes": [
        "普通"
    ],
    "trainDestinations": [
        "大崎(環状線)",
        "池袋",
        "品川"
    ],
    "isHoliday": false,
    "trainTimes": [
        437,
        505,
        523,
        543,
        556,
        603,
        610,
        617,
        623,
        629,
        634,
        640,
        645,
        650,
        655,
        701,
        705,
        708,
        712,
        716,
        719,
        723,
        727,
        731,
        735,
        739,
        742,
        746,
        749,
        753,
        756,
        800,
        803,
        807,
        810,
        814,
        817,
        821,
        824,
        828,
        831,
        835,
        838,
        842,
        846,
        849,
        853,
        856,
        900,
        903,
        907,
        910,
        914,
        917,
        921,
        925,
        929,
        933,
        938,
        942,
        946,
        951,
        955,
        959,
        1004,
        1009,
        1012,
        1016,
        1020,
        1024,
        1029,
        1033,
        1037,
        1042,
        1047,
        1052,
        1057,
        1102,
        1107,
        1112,
        1117,
        1122,
        1127,
        1132,
        1137,
        1142,
        1147,
        1152,
        1157,
        1202,
        1207,
        1212,
        1217,
        1222,
        1227,
        1232,
        1237,
        1242,
        1247,
        1252,
        1257,
        1302,
        1307,
        1312,
        1317,
        1322,
        1327,
        1332,
        1337,
        1342,
        1347,
        1352,
        1357,
        1402,
        1407,
        1412,
        1417,
        1422,
        1427,
        1432,
        1437,
        1442,
        1447,
        1452,
        1457,
        1502,
        1507,
        1512,
        1517,
        1522,
        1527,
        1532,
        1537,
        1542,
        1547,
        1552,
        1557,
        1602,
        1607,
        1612,
        1617,
        1622,
        1627,
        1632,
        1636,
        1640,
        1643,
        1647,
        1650,
        1653,
        1657,
        1700,
        1704,
        1708,
        1711,
        1715,
        1719,
        1722,
        1725,
        1729,
        1732,
        1735,
        1739,
        1742,
        1745,
        1749,
        1752,
        1756,
        1759,
        1802,
        1806,
        1809,
        1812,
        1816,
        1819,
        1822,
        1826,
        1829,
        1832,
        1836,
        1839,
        1842,
        1846,
        1849,
        1852,
        1856,
        1859,
        1902,
        1906,
        1909,
        1912,
        1916,
        1919,
        1922,
        1926,
        1929,
        1932,
        1936,
        1939,
        1942,
        1946,
        1949,
        1952,
        1956,
        1959,
        2002,
        2006,
        2009,
        2012,
        2016,
        2019,
        2022,
        2026,
        2029,
        2032,
        2036,
        2039,
        2042,
        2046,
        2049,
        2052,
        2056,
        2059,
        2102,
        2106,
        2109,
        2112,
        2116,
        2119,
        2123,
        2127,
        2131,
        2136,
        2139,
        2142,
        2146,
        2149,
        2152,
        2156,
        2200,
        2204,
        2207,
        2211,
        2216,
        2219,
        2222,
        2226,
        2230,
        2234,
        2238,
        2242,
        2246,
        2251,
        2256,
        2259,
        2303,
        2307,
        2311,
        2316,
        2319,
        2323,
        2327,
        2331,
        2335,
        2339,
        2343,
        2347,
        2350,
        2355,
        1,
        7,
        11,
        16,
        20,
        24,
        29,
        33
    ],
    "trainDetails": {
        "0437": {
            "type": 0,
            "dst": 0
        },
        "0505": {
            "type": 0,
            "dst": 0
        },
        "0523": {
            "type": 0,
            "dst": 0
        },
        "0543": {
            "type": 0,
            "dst": 0
        },
        "0556": {
            "type": 0,
            "dst": 0
        },
        "0603": {
            "type": 0,
            "dst": 0
        },
        "0610": {
            "type": 0,
            "dst": 0
        },
        "0617": {
            "type": 0,
            "dst": 0
        },
        "0623": {
            "type": 0,
            "dst": 0
        },
        "0629": {
            "type": 0,
            "dst": 0
        },
        "0634": {
            "type": 0,
            "dst": 0
        },
        "0640": {
            "type": 0,
            "dst": 0
        },
        "0645": {
            "type": 0,
            "dst": 0
        },
        "0650": {
            "type": 0,
            "dst": 0
        },
        "0655": {
            "type": 0,
            "dst": 0
        },
        "0701": {
            "type": 0,
            "dst": 0
        },
        "0705": {
            "type": 0,
            "dst": 0
        },
        "0708": {
            "type": 0,
            "dst": 0
        },
        "0712": {
            "type": 0,
            "dst": 0
        },
        "0716": {
            "type": 0,
            "dst": 0
        },
        "0719": {
            "type": 0,
            "dst": 0
        },
        "0723": {
            "type": 0,
            "dst": 0
        },
        "0727": {
            "type": 0,
            "dst": 0
        },
        "0731": {
            "type": 0,
            "dst": 0
        },
        "0735": {
            "type": 0,
            "dst": 0
        },
        "0739": {
            "type": 0,
            "dst": 0
        },
        "0742": {
            "type": 0,
            "dst": 0
        },
        "0746": {
            "type": 0,
            "dst": 0
        },
        "0749": {
            "type": 0,
            "dst": 0
        },
        "0753": {
            "type": 0,
            "dst": 0
        },
        "0756": {
            "type": 0,
            "dst": 0
        },
        "0800": {
            "type": 0,
            "dst": 0
        },
        "0803": {
            "type": 0,
            "dst": 0
        },
        "0807": {
            "type": 0,
            "dst": 0
        },
        "0810": {
            "type": 0,
            "dst": 0
        },
        "0814": {
            "type": 0,
            "dst": 0
        },
        "0817": {
            "type": 0,
            "dst": 0
        },
        "0821": {
            "type": 0,
            "dst": 0
        },
        "0824": {
            "type": 0,
            "dst": 0
        },
        "0828": {
            "type": 0,
            "dst": 0
        },
        "0831": {
            "type": 0,
            "dst": 0
        },
        "0835": {
            "type": 0,
            "dst": 0
        },
        "0838": {
            "type": 0,
            "dst": 0
        },
        "0842": {
            "type": 0,
            "dst": 0
        },
        "0846": {
            "type": 0,
            "dst": 0
        },
        "0849": {
            "type": 0,
            "dst": 0
        },
        "0853": {
            "type": 0,
            "dst": 0
        },
        "0856": {
            "type": 0,
            "dst": 0
        },
        "0900": {
            "type": 0,
            "dst": 0
        },
        "0903": {
            "type": 0,
            "dst": 0
        },
        "0907": {
            "type": 0,
            "dst": 0
        },
        "0910": {
            "type": 0,
            "dst": 0
        },
        "0914": {
            "type": 0,
            "dst": 0
        },
        "0917": {
            "type": 0,
            "dst": 0
        },
        "0921": {
            "type": 0,
            "dst": 0
        },
        "0925": {
            "type": 0,
            "dst": 0
        },
        "0929": {
            "type": 0,
            "dst": 0
        },
        "0933": {
            "type": 0,
            "dst": 0
        },
        "0938": {
            "type": 0,
            "dst": 0
        },
        "0942": {
            "type": 0,
            "dst": 0
        },
        "0946": {
            "type": 0,
            "dst": 0
        },
        "0951": {
            "type": 0,
            "dst": 0
        },
        "0955": {
            "type": 0,
            "dst": 0
        },
        "0959": {
            "type": 0,
            "dst": 0
        },
        "1004": {
            "type": 0,
            "dst": 0
        },
        "1009": {
            "type": 0,
            "dst": 0
        },
        "1012": {
            "type": 0,
            "dst": 0
        },
        "1016": {
            "type": 0,
            "dst": 0
        },
        "1020": {
            "type": 0,
            "dst": 0
        },
        "1024": {
            "type": 0,
            "dst": 0
        },
        "1029": {
            "type": 0,
            "dst": 0
        },
        "1033": {
            "type": 0,
            "dst": 0
        },
        "1037": {
            "type": 0,
            "dst": 0
        },
        "1042": {
            "type": 0,
            "dst": 0
        },
        "1047": {
            "type": 0,
            "dst": 0
        },
        "1052": {
            "type": 0,
            "dst": 0
        },
        "1057": {
            "type": 0,
            "dst": 0
        },
        "1102": {
            "type": 0,
            "dst": 0
        },
        "1107": {
            "type": 0,
            "dst": 0
        },
        "1112": {
            "type": 0,
            "dst": 0
        },
        "1117": {
            "type": 0,
            "dst": 0
        },
        "1122": {
            "type": 0,
            "dst": 0
        },
        "1127": {
            "type": 0,
            "dst": 0
        },
        "1132": {
            "type": 0,
            "dst": 0
        },
        "1137": {
            "type": 0,
            "dst": 0
        },
        "1142": {
            "type": 0,
            "dst": 0
        },
        "1147": {
            "type": 0,
            "dst": 0
        },
        "1152": {
            "type": 0,
            "dst": 0
        },
        "1157": {
            "type": 0,
            "dst": 0
        },
        "1202": {
            "type": 0,
            "dst": 0
        },
        "1207": {
            "type": 0,
            "dst": 0
        },
        "1212": {
            "type": 0,
            "dst": 0
        },
        "1217": {
            "type": 0,
            "dst": 0
        },
        "1222": {
            "type": 0,
            "dst": 0
        },
        "1227": {
            "type": 0,
            "dst": 0
        },
        "1232": {
            "type": 0,
            "dst": 0
        },
        "1237": {
            "type": 0,
            "dst": 0
        },
        "1242": {
            "type": 0,
            "dst": 0
        },
        "1247": {
            "type": 0,
            "dst": 0
        },
        "1252": {
            "type": 0,
            "dst": 0
        },
        "1257": {
            "type": 0,
            "dst": 0
        },
        "1302": {
            "type": 0,
            "dst": 0
        },
        "1307": {
            "type": 0,
            "dst": 0
        },
        "1312": {
            "type": 0,
            "dst": 0
        },
        "1317": {
            "type": 0,
            "dst": 0
        },
        "1322": {
            "type": 0,
            "dst": 0
        },
        "1327": {
            "type": 0,
            "dst": 0
        },
        "1332": {
            "type": 0,
            "dst": 0
        },
        "1337": {
            "type": 0,
            "dst": 0
        },
        "1342": {
            "type": 0,
            "dst": 0
        },
        "1347": {
            "type": 0,
            "dst": 0
        },
        "1352": {
            "type": 0,
            "dst": 0
        },
        "1357": {
            "type": 0,
            "dst": 0
        },
        "1402": {
            "type": 0,
            "dst": 0
        },
        "1407": {
            "type": 0,
            "dst": 0
        },
        "1412": {
            "type": 0,
            "dst": 0
        },
        "1417": {
            "type": 0,
            "dst": 0
        },
        "1422": {
            "type": 0,
            "dst": 0
        },
        "1427": {
            "type": 0,
            "dst": 0
        },
        "1432": {
            "type": 0,
            "dst": 0
        },
        "1437": {
            "type": 0,
            "dst": 0
        },
        "1442": {
            "type": 0,
            "dst": 0
        },
        "1447": {
            "type": 0,
            "dst": 0
        },
        "1452": {
            "type": 0,
            "dst": 0
        },
        "1457": {
            "type": 0,
            "dst": 0
        },
        "1502": {
            "type": 0,
            "dst": 0
        },
        "1507": {
            "type": 0,
            "dst": 0
        },
        "1512": {
            "type": 0,
            "dst": 0
        },
        "1517": {
            "type": 0,
            "dst": 0
        },
        "1522": {
            "type": 0,
            "dst": 0
        },
        "1527": {
            "type": 0,
            "dst": 0
        },
        "1532": {
            "type": 0,
            "dst": 0
        },
        "1537": {
            "type": 0,
            "dst": 0
        },
        "1542": {
            "type": 0,
            "dst": 0
        },
        "1547": {
            "type": 0,
            "dst": 0
        },
        "1552": {
            "type": 0,
            "dst": 0
        },
        "1557": {
            "type": 0,
            "dst": 0
        },
        "1602": {
            "type": 0,
            "dst": 0
        },
        "1607": {
            "type": 0,
            "dst": 0
        },
        "1612": {
            "type": 0,
            "dst": 0
        },
        "1617": {
            "type": 0,
            "dst": 0
        },
        "1622": {
            "type": 0,
            "dst": 0
        },
        "1627": {
            "type": 0,
            "dst": 0
        },
        "1632": {
            "type": 0,
            "dst": 0
        },
        "1636": {
            "type": 0,
            "dst": 0
        },
        "1640": {
            "type": 0,
            "dst": 0
        },
        "1643": {
            "type": 0,
            "dst": 0
        },
        "1647": {
            "type": 0,
            "dst": 0
        },
        "1650": {
            "type": 0,
            "dst": 0
        },
        "1653": {
            "type": 0,
            "dst": 0
        },
        "1657": {
            "type": 0,
            "dst": 0
        },
        "1700": {
            "type": 0,
            "dst": 0
        },
        "1704": {
            "type": 0,
            "dst": 0
        },
        "1708": {
            "type": 0,
            "dst": 0
        },
        "1711": {
            "type": 0,
            "dst": 0
        },
        "1715": {
            "type": 0,
            "dst": 0
        },
        "1719": {
            "type": 0,
            "dst": 0
        },
        "1722": {
            "type": 0,
            "dst": 0
        },
        "1725": {
            "type": 0,
            "dst": 0
        },
        "1729": {
            "type": 0,
            "dst": 0
        },
        "1732": {
            "type": 0,
            "dst": 0
        },
        "1735": {
            "type": 0,
            "dst": 0
        },
        "1739": {
            "type": 0,
            "dst": 0
        },
        "1742": {
            "type": 0,
            "dst": 0
        },
        "1745": {
            "type": 0,
            "dst": 0
        },
        "1749": {
            "type": 0,
            "dst": 0
        },
        "1752": {
            "type": 0,
            "dst": 0
        },
        "1756": {
            "type": 0,
            "dst": 0
        },
        "1759": {
            "type": 0,
            "dst": 0
        },
        "1802": {
            "type": 0,
            "dst": 0
        },
        "1806": {
            "type": 0,
            "dst": 0
        },
        "1809": {
            "type": 0,
            "dst": 0
        },
        "1812": {
            "type": 0,
            "dst": 0
        },
        "1816": {
            "type": 0,
            "dst": 0
        },
        "1819": {
            "type": 0,
            "dst": 0
        },
        "1822": {
            "type": 0,
            "dst": 0
        },
        "1826": {
            "type": 0,
            "dst": 0
        },
        "1829": {
            "type": 0,
            "dst": 0
        },
        "1832": {
            "type": 0,
            "dst": 0
        },
        "1836": {
            "type": 0,
            "dst": 0
        },
        "1839": {
            "type": 0,
            "dst": 0
        },
        "1842": {
            "type": 0,
            "dst": 0
        },
        "1846": {
            "type": 0,
            "dst": 0
        },
        "1849": {
            "type": 0,
            "dst": 0
        },
        "1852": {
            "type": 0,
            "dst": 0
        },
        "1856": {
            "type": 0,
            "dst": 0
        },
        "1859": {
            "type": 0,
            "dst": 0
        },
        "1902": {
            "type": 0,
            "dst": 0
        },
        "1906": {
            "type": 0,
            "dst": 0
        },
        "1909": {
            "type": 0,
            "dst": 0
        },
        "1912": {
            "type": 0,
            "dst": 0
        },
        "1916": {
            "type": 0,
            "dst": 0
        },
        "1919": {
            "type": 0,
            "dst": 0
        },
        "1922": {
            "type": 0,
            "dst": 0
        },
        "1926": {
            "type": 0,
            "dst": 0
        },
        "1929": {
            "type": 0,
            "dst": 0
        },
        "1932": {
            "type": 0,
            "dst": 0
        },
        "1936": {
            "type": 0,
            "dst": 0
        },
        "1939": {
            "type": 0,
            "dst": 0
        },
        "1942": {
            "type": 0,
            "dst": 0
        },
        "1946": {
            "type": 0,
            "dst": 0
        },
        "1949": {
            "type": 0,
            "dst": 0
        },
        "1952": {
            "type": 0,
            "dst": 0
        },
        "1956": {
            "type": 0,
            "dst": 0
        },
        "1959": {
            "type": 0,
            "dst": 0
        },
        "2002": {
            "type": 0,
            "dst": 0
        },
        "2006": {
            "type": 0,
            "dst": 0
        },
        "2009": {
            "type": 0,
            "dst": 0
        },
        "2012": {
            "type": 0,
            "dst": 0
        },
        "2016": {
            "type": 0,
            "dst": 0
        },
        "2019": {
            "type": 0,
            "dst": 0
        },
        "2022": {
            "type": 0,
            "dst": 0
        },
        "2026": {
            "type": 0,
            "dst": 0
        },
        "2029": {
            "type": 0,
            "dst": 0
        },
        "2032": {
            "type": 0,
            "dst": 0
        },
        "2036": {
            "type": 0,
            "dst": 0
        },
        "2039": {
            "type": 0,
            "dst": 0
        },
        "2042": {
            "type": 0,
            "dst": 0
        },
        "2046": {
            "type": 0,
            "dst": 0
        },
        "2049": {
            "type": 0,
            "dst": 0
        },
        "2052": {
            "type": 0,
            "dst": 0
        },
        "2056": {
            "type": 0,
            "dst": 0
        },
        "2059": {
            "type": 0,
            "dst": 0
        },
        "2102": {
            "type": 0,
            "dst": 0
        },
        "2106": {
            "type": 0,
            "dst": 0
        },
        "2109": {
            "type": 0,
            "dst": 0
        },
        "2112": {
            "type": 0,
            "dst": 0
        },
        "2116": {
            "type": 0,
            "dst": 0
        },
        "2119": {
            "type": 0,
            "dst": 0
        },
        "2123": {
            "type": 0,
            "dst": 0
        },
        "2127": {
            "type": 0,
            "dst": 0
        },
        "2131": {
            "type": 0,
            "dst": 0
        },
        "2136": {
            "type": 0,
            "dst": 0
        },
        "2139": {
            "type": 0,
            "dst": 0
        },
        "2142": {
            "type": 0,
            "dst": 0
        },
        "2146": {
            "type": 0,
            "dst": 0
        },
        "2149": {
            "type": 0,
            "dst": 0
        },
        "2152": {
            "type": 0,
            "dst": 0
        },
        "2156": {
            "type": 0,
            "dst": 0
        },
        "2200": {
            "type": 0,
            "dst": 0
        },
        "2204": {
            "type": 0,
            "dst": 0
        },
        "2207": {
            "type": 0,
            "dst": 0
        },
        "2211": {
            "type": 0,
            "dst": 0
        },
        "2216": {
            "type": 0,
            "dst": 0
        },
        "2219": {
            "type": 0,
            "dst": 0
        },
        "2222": {
            "type": 0,
            "dst": 0
        },
        "2226": {
            "type": 0,
            "dst": 0
        },
        "2230": {
            "type": 0,
            "dst": 0
        },
        "2234": {
            "type": 0,
            "dst": 0
        },
        "2238": {
            "type": 0,
            "dst": 0
        },
        "2242": {
            "type": 0,
            "dst": 0
        },
        "2246": {
            "type": 0,
            "dst": 0
        },
        "2251": {
            "type": 0,
            "dst": 0
        },
        "2256": {
            "type": 0,
            "dst": 0
        },
        "2259": {
            "type": 0,
            "dst": 0
        },
        "2303": {
            "type": 0,
            "dst": 0
        },
        "2307": {
            "type": 0,
            "dst": 0
        },
        "2311": {
            "type": 0,
            "dst": 0
        },
        "2316": {
            "type": 0,
            "dst": 0
        },
        "2319": {
            "type": 0,
            "dst": 0
        },
        "2323": {
            "type": 0,
            "dst": 0
        },
        "2327": {
            "type": 0,
            "dst": 0
        },
        "2331": {
            "type": 0,
            "dst": 0
        },
        "2335": {
            "type": 0,
            "dst": 0
        },
        "2339": {
            "type": 0,
            "dst": 0
        },
        "2343": {
            "type": 0,
            "dst": 0
        },
        "2347": {
            "type": 0,
            "dst": 0
        },
        "2350": {
            "type": 0,
            "dst": 0
        },
        "2355": {
            "type": 0,
            "dst": 0
        },
        "0001": {
            "type": 0,
            "dst": 0
        },
        "0007": {
            "type": 0,
            "dst": 0
        },
        "0011": {
            "type": 0,
            "dst": 0
        },
        "0016": {
            "type": 0,
            "dst": 0
        },
        "0020": {
            "type": 0,
            "dst": 0
        },
        "0024": {
            "type": 0,
            "dst": 2
        },
        "0029": {
            "type": 0,
            "dst": 2
        },
        "0033": {
            "type": 0,
            "dst": 2
        }
    }
}