{
    "stationName": "八王子",
    "lineName": "中央線（快速） 下り",
    "trainTypes": [
        "特急 かつうらひな祭り",
        "特急 さわら・かしま",
        "特別快速 ホリデー快速おくたま5号",
        "快速",
        "青梅特快",
        "中央特快",
        "特急 新宿わかしお",
        "特別快速 ホリデー快速あきがわ5号",
        "特急 新宿さざなみ4号",
        "特別快速 ホリデー快速あきがわ3号",
        "普通",
        "特別快速 ホリデー快速おくたま1号",
        "普通 むさしの号",
        "特急 新宿さざなみ2号",
        "特別快速 ホリデー快速あきがわ1号",
        "特別快速 ホリデー快速おくたま3号"
    ],
    "trainDestinations": [
        "豊田",
        "八王子",
        "高尾",
        "立川",
        "武蔵小金井",
        "国分寺",
        "新宿"
    ],
    "isHoliday": true,
    "trainSchedules": {
        "0452": {
            "type": 3,
            "dst": 2
        },
        "0507": {
            "type": 3,
            "dst": 2
        },
        "0526": {
            "type": 3,
            "dst": 2
        },
        "0534": {
            "type": 3,
            "dst": 2
        },
        "0539": {
            "type": 3,
            "dst": 2
        },
        "0551": {
            "type": 3,
            "dst": 2
        },
        "0604": {
            "type": 3,
            "dst": 2
        },
        "0615": {
            "type": 3,
            "dst": 2
        },
        "0620": {
            "type": 3,
            "dst": 2
        },
        "0629": {
            "type": 3,
            "dst": 2
        },
        "0635": {
            "type": 10,
            "dst": 2
        },
        "0644": {
            "type": 3,
            "dst": 2
        },
        "0700": {
            "type": 3,
            "dst": 2
        },
        "0653": {
            "type": 5,
            "dst": 2
        },
        "0704": {
            "type": 10,
            "dst": 2
        },
        "0715": {
            "type": 3,
            "dst": 2
        },
        "0724": {
            "type": 3,
            "dst": 2
        },
        "0739": {
            "type": 3,
            "dst": 2
        },
        "0749": {
            "type": 3,
            "dst": 2
        },
        "0753": {
            "type": 3,
            "dst": 2
        },
        "0805": {
            "type": 3,
            "dst": 2
        },
        "0758": {
            "type": 5,
            "dst": 2
        },
        "0811": {
            "type": 10,
            "dst": 2
        },
        "0819": {
            "type": 3,
            "dst": 2
        },
        "0826": {
            "type": 3,
            "dst": 1
        },
        "0840": {
            "type": 3,
            "dst": 2
        },
        "0828": {
            "type": 5,
            "dst": 2
        },
        "0843": {
            "type": 3,
            "dst": 2
        },
        "0854": {
            "type": 3,
            "dst": 2
        },
        "0900": {
            "type": 3,
            "dst": 1
        },
        "0912": {
            "type": 3,
            "dst": 2
        },
        "0902": {
            "type": 5,
            "dst": 2
        },
        "0924": {
            "type": 3,
            "dst": 2
        },
        "0915": {
            "type": 5,
            "dst": 2
        },
        "0940": {
            "type": 3,
            "dst": 2
        },
        "0944": {
            "type": 12,
            "dst": 1
        },
        "0930": {
            "type": 5,
            "dst": 2
        },
        "0949": {
            "type": 3,
            "dst": 2
        },
        "1000": {
            "type": 3,
            "dst": 2
        },
        "1010": {
            "type": 3,
            "dst": 2
        },
        "0953": {
            "type": 5,
            "dst": 2
        },
        "1012": {
            "type": 3,
            "dst": 1
        },
        "1018": {
            "type": 3,
            "dst": 2
        },
        "1023": {
            "type": 3,
            "dst": 2
        },
        "1040": {
            "type": 3,
            "dst": 1
        },
        "1027": {
            "type": 5,
            "dst": 2
        },
        "1045": {
            "type": 3,
            "dst": 2
        },
        "1052": {
            "type": 3,
            "dst": 2
        },
        "1057": {
            "type": 5,
            "dst": 2
        },
        "1118": {
            "type": 3,
            "dst": 1
        },
        "1113": {
            "type": 5,
            "dst": 2
        },
        "1134": {
            "type": 3,
            "dst": 1
        },
        "1124": {
            "type": 5,
            "dst": 2
        },
        "1158": {
            "type": 3,
            "dst": 1
        },
        "1141": {
            "type": 5,
            "dst": 2
        },
        "1204": {
            "type": 3,
            "dst": 2
        },
        "1150": {
            "type": 5,
            "dst": 2
        },
        "1216": {
            "type": 3,
            "dst": 1
        },
        "1210": {
            "type": 5,
            "dst": 2
        },
        "1233": {
            "type": 3,
            "dst": 2
        },
        "1225": {
            "type": 5,
            "dst": 2
        },
        "1257": {
            "type": 3,
            "dst": 2
        },
        "1240": {
            "type": 5,
            "dst": 2
        },
        "1247": {
            "type": 5,
            "dst": 2
        },
        "1315": {
            "type": 3,
            "dst": 2
        },
        "1310": {
            "type": 5,
            "dst": 2
        },
        "1334": {
            "type": 3,
            "dst": 1
        },
        "1325": {
            "type": 5,
            "dst": 2
        },
        "1341": {
            "type": 5,
            "dst": 2
        },
        "1405": {
            "type": 3,
            "dst": 2
        },
        "1352": {
            "type": 5,
            "dst": 2
        },
        "1407": {
            "type": 3,
            "dst": 2
        },
        "1422": {
            "type": 3,
            "dst": 2
        },
        "1410": {
            "type": 5,
            "dst": 2
        },
        "1434": {
            "type": 3,
            "dst": 1
        },
        "1425": {
            "type": 5,
            "dst": 2
        },
        "1458": {
            "type": 3,
            "dst": 2
        },
        "1440": {
            "type": 5,
            "dst": 2
        },
        "1504": {
            "type": 3,
            "dst": 2
        },
        "1448": {
            "type": 5,
            "dst": 2
        },
        "1507": {
            "type": 3,
            "dst": 1
        },
        "1519": {
            "type": 3,
            "dst": 2
        },
        "1512": {
            "type": 5,
            "dst": 2
        },
        "1534": {
            "type": 3,
            "dst": 2
        },
        "1525": {
            "type": 5,
            "dst": 2
        },
        "1538": {
            "type": 10,
            "dst": 2
        },
        "1544": {
            "type": 3,
            "dst": 1
        },
        "1541": {
            "type": 5,
            "dst": 2
        },
        "1559": {
            "type": 3,
            "dst": 2
        },
        "1549": {
            "type": 5,
            "dst": 2
        },
        "1619": {
            "type": 3,
            "dst": 2
        },
        "1622": {
            "type": 3,
            "dst": 2
        },
        "1610": {
            "type": 5,
            "dst": 2
        },
        "1635": {
            "type": 3,
            "dst": 2
        },
        "1644": {
            "type": 3,
            "dst": 2
        },
        "1626": {
            "type": 5,
            "dst": 2
        },
        "1653": {
            "type": 3,
            "dst": 2
        },
        "1706": {
            "type": 3,
            "dst": 2
        },
        "1711": {
            "type": 10,
            "dst": 2
        },
        "1658": {
            "type": 5,
            "dst": 2
        },
        "1723": {
            "type": 3,
            "dst": 2
        },
        "1714": {
            "type": 5,
            "dst": 2
        },
        "1739": {
            "type": 3,
            "dst": 2
        },
        "1727": {
            "type": 5,
            "dst": 2
        },
        "1744": {
            "type": 3,
            "dst": 2
        },
        "1753": {
            "type": 3,
            "dst": 2
        },
        "1748": {
            "type": 5,
            "dst": 2
        },
        "1758": {
            "type": 3,
            "dst": 2
        },
        "1809": {
            "type": 3,
            "dst": 2
        },
        "1813": {
            "type": 10,
            "dst": 2
        },
        "1819": {
            "type": 10,
            "dst": 2
        },
        "1815": {
            "type": 3,
            "dst": 1
        },
        "1821": {
            "type": 3,
            "dst": 2
        },
        "1830": {
            "type": 3,
            "dst": 2
        },
        "1825": {
            "type": 5,
            "dst": 2
        },
        "1840": {
            "type": 3,
            "dst": 2
        },
        "1844": {
            "type": 3,
            "dst": 1
        },
        "1848": {
            "type": 3,
            "dst": 2
        },
        "1853": {
            "type": 5,
            "dst": 2
        },
        "1909": {
            "type": 3,
            "dst": 2
        },
        "1901": {
            "type": 5,
            "dst": 2
        },
        "1916": {
            "type": 12,
            "dst": 1
        },
        "1918": {
            "type": 3,
            "dst": 2
        },
        "1930": {
            "type": 3,
            "dst": 2
        },
        "1922": {
            "type": 5,
            "dst": 2
        },
        "1933": {
            "type": 3,
            "dst": 1
        },
        "1940": {
            "type": 10,
            "dst": 2
        },
        "1949": {
            "type": 3,
            "dst": 1
        },
        "1952": {
            "type": 3,
            "dst": 2
        },
        "1944": {
            "type": 5,
            "dst": 2
        },
        "1957": {
            "type": 3,
            "dst": 2
        },
        "2000": {
            "type": 3,
            "dst": 1
        },
        "2010": {
            "type": 3,
            "dst": 2
        },
        "2018": {
            "type": 3,
            "dst": 2
        },
        "2002": {
            "type": 5,
            "dst": 2
        },
        "2029": {
            "type": 3,
            "dst": 2
        },
        "2022": {
            "type": 5,
            "dst": 2
        },
        "2037": {
            "type": 3,
            "dst": 2
        },
        "2043": {
            "type": 12,
            "dst": 1
        },
        "2052": {
            "type": 3,
            "dst": 2
        },
        "2045": {
            "type": 5,
            "dst": 2
        },
        "2109": {
            "type": 3,
            "dst": 2
        },
        "2103": {
            "type": 5,
            "dst": 2
        },
        "2112": {
            "type": 3,
            "dst": 1
        },
        "2129": {
            "type": 3,
            "dst": 2
        },
        "2122": {
            "type": 5,
            "dst": 2
        },
        "2138": {
            "type": 3,
            "dst": 2
        },
        "2141": {
            "type": 3,
            "dst": 1
        },
        "2155": {
            "type": 3,
            "dst": 2
        },
        "2146": {
            "type": 5,
            "dst": 2
        },
        "2206": {
            "type": 5,
            "dst": 2
        },
        "2214": {
            "type": 3,
            "dst": 2
        },
        "2228": {
            "type": 3,
            "dst": 2
        },
        "2222": {
            "type": 5,
            "dst": 2
        },
        "2239": {
            "type": 3,
            "dst": 2
        },
        "2254": {
            "type": 3,
            "dst": 2
        },
        "2245": {
            "type": 5,
            "dst": 2
        },
        "2301": {
            "type": 5,
            "dst": 2
        },
        "2312": {
            "type": 3,
            "dst": 2
        },
        "2329": {
            "type": 3,
            "dst": 2
        },
        "2339": {
            "type": 3,
            "dst": 2
        },
        "2323": {
            "type": 5,
            "dst": 2
        },
        "2350": {
            "type": 5,
            "dst": 2
        },
        "0003": {
            "type": 3,
            "dst": 2
        },
        "0009": {
            "type": 3,
            "dst": 2
        },
        "0018": {
            "type": 3,
            "dst": 2
        },
        "0034": {
            "type": 3,
            "dst": 2
        },
        "0045": {
            "type": 3,
            "dst": 2
        }
    }
}