{
    "stationName": "保土ケ谷",
    "lineName": "湘南新宿ライン 北行",
    "trainTypes": [
        "特急 湘南26号",
        "特急 日光1号",
        "特急 湘南22号",
        "快速",
        "特別快速",
        "特急 スペーシアきぬがわ3号",
        "特急 スペーシアきぬがわ7号",
        "特急 湘南24号",
        "特急 きぬがわ5号",
        "普通"
    ],
    "trainDestinations": [
        "小山"
    ],
    "isHoliday": false,
    "trainSchedules": {
        "6": [
            {
                "minute": 44,
                "type": 9,
                "dst": 0
            }
        ],
        "7": [
            {
                "minute": 20,
                "type": 9,
                "dst": 0
            },
            {
                "minute": 38,
                "type": 9,
                "dst": 0
            },
            {
                "minute": 59,
                "type": 9,
                "dst": 0
            }
        ],
        "8": [
            {
                "minute": 13,
                "type": 9,
                "dst": 0
            },
            {
                "minute": 30,
                "type": 3,
                "dst": 0
            }
        ],
        "9": [
            {
                "minute": 0,
                "type": 9,
                "dst": 0
            },
            {
                "minute": 16,
                "type": 9,
                "dst": 0
            },
            {
                "minute": 54,
                "type": 3,
                "dst": 0
            }
        ],
        "10": [
            {
                "minute": 6,
                "type": 9,
                "dst": 0
            },
            {
                "minute": 32,
                "type": 3,
                "dst": 0
            },
            {
                "minute": 59,
                "type": 9,
                "dst": 0
            }
        ],
        "11": [
            {
                "minute": 29,
                "type": 3,
                "dst": 0
            },
            {
                "minute": 59,
                "type": 9,
                "dst": 0
            }
        ],
        "12": [
            {
                "minute": 29,
                "type": 3,
                "dst": 0
            },
            {
                "minute": 59,
                "type": 9,
                "dst": 0
            }
        ],
        "13": [
            {
                "minute": 29,
                "type": 3,
                "dst": 0
            },
            {
                "minute": 59,
                "type": 9,
                "dst": 0
            }
        ],
        "14": [
            {
                "minute": 29,
                "type": 3,
                "dst": 0
            },
            {
                "minute": 59,
                "type": 9,
                "dst": 0
            }
        ],
        "15": [
            {
                "minute": 28,
                "type": 3,
                "dst": 0
            },
            {
                "minute": 58,
                "type": 9,
                "dst": 0
            }
        ],
        "16": [
            {
                "minute": 29,
                "type": 3,
                "dst": 0
            },
            {
                "minute": 59,
                "type": 9,
                "dst": 0
            }
        ],
        "17": [
            {
                "minute": 29,
                "type": 9,
                "dst": 0
            },
            {
                "minute": 57,
                "type": 9,
                "dst": 0
            }
        ],
        "18": [
            {
                "minute": 29,
                "type": 9,
                "dst": 0
            },
            {
                "minute": 58,
                "type": 9,
                "dst": 0
            }
        ],
        "19": [
            {
                "minute": 29,
                "type": 9,
                "dst": 0
            },
            {
                "minute": 59,
                "type": 9,
                "dst": 0
            }
        ],
        "20": [
            {
                "minute": 43,
                "type": 9,
                "dst": 0
            }
        ],
        "21": [
            {
                "minute": 37,
                "type": 9,
                "dst": 0
            }
        ],
        "22": [
            {
                "minute": 24,
                "type": 9,
                "dst": 0
            }
        ]
    }
}